<?xml version="1.0" encoding="UTF-8" standalone="yes"?>
<idPkg:Story xmlns:idPkg="http://ns.adobe.com/AdobeInDesign/idml/1.0/packaging" DOMVersion="14.0">
	<Story Self="u23e" UserText="true" IsEndnoteStory="false" AppliedTOCStyle="n" TrackChanges="false" StoryTitle="$ID/" AppliedNamedGrid="n">
		<StoryPreference OpticalMarginAlignment="false" OpticalMarginSize="12" FrameType="TextFrameType" StoryOrientation="Horizontal" StoryDirection="LeftToRightDirection" />
		<InCopyExportOption IncludeGraphicProxies="true" IncludeAllResources="false" />
		<ParagraphStyleRange AppliedParagraphStyle="ParagraphStyle/$ID/NormalParagraphStyle" Hyphenation="false">
			<CharacterStyleRange AppliedCharacterStyle="CharacterStyle/$ID/[No character style]" PointSize="10" Tracking="-10" Capitalization="AllCaps">
				<Properties>
					<Leading type="unit">14</Leading>
					<AppliedFont type="string">Montserrat</AppliedFont>
				</Properties>
				<Content>Votre pouvoir d’achat</Content>
				<Br />
			</CharacterStyleRange>
		</ParagraphStyleRange>
		<ParagraphStyleRange AppliedParagraphStyle="ParagraphStyle/$ID/NormalParagraphStyle" Hyphenation="false" SpaceBefore="2.834645669291339" SpaceAfter="5.669291338582678">
			<CharacterStyleRange AppliedCharacterStyle="CharacterStyle/$ID/[No character style]" FontStyle="Bold" PointSize="10" Tracking="-10">
				<Properties>
					<Leading type="unit">14</Leading>
					<AppliedFont type="string">Montserrat</AppliedFont>
				</Properties>
				<Content>• La baisse des taxes et des impôts</Content>
			</CharacterStyleRange>
			<CharacterStyleRange AppliedCharacterStyle="CharacterStyle/$ID/[No character style]" PointSize="10" Tracking="-10">
				<Properties>
					<Leading type="unit">14</Leading>
					<AppliedFont type="string">Montserrat</AppliedFont>
				</Properties>
				<Content> grâce à l’arrêt des gaspillages et des privilèges indécents</Content>
				<Br />
			</CharacterStyleRange>
		</ParagraphStyleRange>
		<ParagraphStyleRange AppliedParagraphStyle="ParagraphStyle/$ID/NormalParagraphStyle" Hyphenation="false" SpaceBefore="2.834645669291339" SpaceAfter="2.834645669291339">
			<CharacterStyleRange AppliedCharacterStyle="CharacterStyle/$ID/[No character style]" FontStyle="Bold" PointSize="10" Tracking="-10">
				<Properties>
					<Leading type="unit">14</Leading>
					<AppliedFont type="string">Montserrat</AppliedFont>
				</Properties>
				<Content>• <?ACE 7?>La Ré-indexation de vos retraites sur l’inflation :</Content>
			</CharacterStyleRange>
			<CharacterStyleRange AppliedCharacterStyle="CharacterStyle/$ID/[No character style]" PointSize="10" Tracking="-10">
				<Properties>
					<Leading type="unit">14</Leading>
					<AppliedFont type="string">Montserrat</AppliedFont>
				</Properties>
				<Content>  pas de retraites en dessous  de 1000 euros net</Content>
				<Br />
			</CharacterStyleRange>
			<CharacterStyleRange AppliedCharacterStyle="CharacterStyle/$ID/[No character style]" FontStyle="Bold" PointSize="10" Tracking="-10">
				<Properties>
					<Leading type="unit">14</Leading>
					<AppliedFont type="string">Montserrat</AppliedFont>
				</Properties>
				<Content>• <?ACE 7?>L’augmentation immédiate  de vos salaires net de 100 euros</Content>
			</CharacterStyleRange>
			<CharacterStyleRange AppliedCharacterStyle="CharacterStyle/$ID/[No character style]" PointSize="10" Tracking="-10">
				<Properties>
					<Leading type="unit">14</Leading>
					<AppliedFont type="string">Montserrat</AppliedFont>
				</Properties>
				<Content> par une baisse des charges financée par une taxe </Content>
			</CharacterStyleRange>
			<CharacterStyleRange AppliedCharacterStyle="CharacterStyle/$ID/[No character style]" FontStyle="Bold" PointSize="10" Tracking="-10">
				<Properties>
					<Leading type="unit">14</Leading>
					<AppliedFont type="string">Montserrat</AppliedFont>
				</Properties>
				<Content> </Content>
			</CharacterStyleRange>
			<CharacterStyleRange AppliedCharacterStyle="CharacterStyle/$ID/[No character style]" PointSize="10" Tracking="-10">
				<Properties>
					<Leading type="unit">14</Leading>
					<AppliedFont type="string">Montserrat</AppliedFont>
				</Properties>
				<Content>à l’importation</Content>
				<Br />
			</CharacterStyleRange>
		</ParagraphStyleRange>
		<ParagraphStyleRange AppliedParagraphStyle="ParagraphStyle/$ID/NormalParagraphStyle" Hyphenation="false" SpaceBefore="2.834645669291339">
			<CharacterStyleRange AppliedCharacterStyle="CharacterStyle/$ID/[No character style]" FontStyle="Bold" PointSize="10" Tracking="-10">
				<Properties>
					<Leading type="unit">14</Leading>
					<AppliedFont type="string">Montserrat</AppliedFont>
				</Properties>
				<Content>• <?ACE 7?>Le contrôle effectif  et l’évaluation systématique  des dépenses publiques</Content>
			</CharacterStyleRange>
			<CharacterStyleRange AppliedCharacterStyle="CharacterStyle/$ID/[No character style]" PointSize="10" Tracking="-10">
				<Properties>
					<Leading type="unit">14</Leading>
					<AppliedFont type="string">Montserrat</AppliedFont>
				</Properties>
				<Br />
			</CharacterStyleRange>
		</ParagraphStyleRange>
		<ParagraphStyleRange AppliedParagraphStyle="ParagraphStyle/$ID/NormalParagraphStyle" Hyphenation="false" SpaceBefore="14.173228346456694">
			<CharacterStyleRange AppliedCharacterStyle="CharacterStyle/$ID/[No character style]" PointSize="10" Tracking="-10" Capitalization="AllCaps">
				<Properties>
					<Leading type="unit">14</Leading>
					<AppliedFont type="string">Montserrat</AppliedFont>
				</Properties>
				<Content>Votre identité</Content>
				<Br />
			</CharacterStyleRange>
		</ParagraphStyleRange>
		<ParagraphStyleRange AppliedParagraphStyle="ParagraphStyle/$ID/NormalParagraphStyle" Hyphenation="false" SpaceBefore="2.834645669291339" SpaceAfter="2.834645669291339">
			<CharacterStyleRange AppliedCharacterStyle="CharacterStyle/$ID/[No character style]" FontStyle="Bold" PointSize="10" Tracking="-10">
				<Properties>
					<Leading type="unit">14</Leading>
					<AppliedFont type="string">Montserrat</AppliedFont>
				</Properties>
				<Content>• <?ACE 7?>L’arrêt de l’immigration </Content>
				<Br />
			</CharacterStyleRange>
		</ParagraphStyleRange>
		<ParagraphStyleRange AppliedParagraphStyle="ParagraphStyle/$ID/NormalParagraphStyle" Hyphenation="false" SpaceAfter="2.834645669291339">
			<CharacterStyleRange AppliedCharacterStyle="CharacterStyle/$ID/[No character style]" FontStyle="Bold" PointSize="10" Tracking="-10">
				<Properties>
					<Leading type="unit">14</Leading>
					<AppliedFont type="string">Montserrat</AppliedFont>
				</Properties>
				<Content>• <?ACE 7?>Le refus</Content>
			</CharacterStyleRange>
			<CharacterStyleRange AppliedCharacterStyle="CharacterStyle/$ID/[No character style]" PointSize="10" Tracking="-10">
				<Properties>
					<Leading type="unit">14</Leading>
					<AppliedFont type="string">Montserrat</AppliedFont>
				</Properties>
				<Content> du communautarisme</Content>
				<Br />
			</CharacterStyleRange>
		</ParagraphStyleRange>
		<ParagraphStyleRange AppliedParagraphStyle="ParagraphStyle/$ID/NormalParagraphStyle" Hyphenation="false">
			<CharacterStyleRange AppliedCharacterStyle="CharacterStyle/$ID/[No character style]" PointSize="10" Tracking="-10">
				<Properties>
					<Leading type="unit">14</Leading>
					<AppliedFont type="string">Montserrat</AppliedFont>
				</Properties>
				<Content>• <?ACE 7?>La défense de </Content>
			</CharacterStyleRange>
			<CharacterStyleRange AppliedCharacterStyle="CharacterStyle/$ID/[No character style]" FontStyle="Bold" PointSize="10" Tracking="-10">
				<Properties>
					<Leading type="unit">14</Leading>
					<AppliedFont type="string">Montserrat</AppliedFont>
				</Properties>
				<Content>nos traditions  </Content>
			</CharacterStyleRange>
			<CharacterStyleRange AppliedCharacterStyle="CharacterStyle/$ID/[No character style]" PointSize="10" Tracking="-10">
				<Properties>
					<Leading type="unit">14</Leading>
					<AppliedFont type="string">Montserrat</AppliedFont>
				</Properties>
				<Content>et de </Content>
			</CharacterStyleRange>
			<CharacterStyleRange AppliedCharacterStyle="CharacterStyle/$ID/[No character style]" FontStyle="Bold" PointSize="10" Tracking="-10">
				<Properties>
					<Leading type="unit">14</Leading>
					<AppliedFont type="string">Montserrat</AppliedFont>
				</Properties>
				<Content>la fierté d’être français</Content>
				<Br />
			</CharacterStyleRange>
			<CharacterStyleRange AppliedCharacterStyle="CharacterStyle/$ID/[No character style]" PointSize="10" Tracking="-10" Capitalization="AllCaps">
				<Properties>
					<Leading type="unit">14</Leading>
					<AppliedFont type="string">Montserrat</AppliedFont>
				</Properties>
				<Br />
			</CharacterStyleRange>
		</ParagraphStyleRange>
		<ParagraphStyleRange AppliedParagraphStyle="ParagraphStyle/$ID/NormalParagraphStyle" Hyphenation="false" SpaceBefore="2.834645669291339">
			<CharacterStyleRange AppliedCharacterStyle="CharacterStyle/$ID/[No character style]" PointSize="10" Tracking="-10" Capitalization="AllCaps">
				<Properties>
					<Leading type="unit">14</Leading>
					<AppliedFont type="string">Montserrat</AppliedFont>
				</Properties>
				<Content>Vos services publics  de proximité</Content>
				<Br />
			</CharacterStyleRange>
		</ParagraphStyleRange>
		<ParagraphStyleRange AppliedParagraphStyle="ParagraphStyle/$ID/NormalParagraphStyle" Hyphenation="false" SpaceBefore="2.834645669291339" SpaceAfter="2.834645669291339">
			<CharacterStyleRange AppliedCharacterStyle="CharacterStyle/$ID/[No character style]" PointSize="10" Tracking="-10">
				<Properties>
					<Leading type="unit">14</Leading>
					<AppliedFont type="string">Montserrat</AppliedFont>
				</Properties>
				<Content>• <?ACE 7?>La défense de </Content>
			</CharacterStyleRange>
			<CharacterStyleRange AppliedCharacterStyle="CharacterStyle/$ID/[No character style]" FontStyle="Bold" PointSize="10" Tracking="-10">
				<Properties>
					<Leading type="unit">14</Leading>
					<AppliedFont type="string">Montserrat</AppliedFont>
				</Properties>
				<Content>nos communes</Content>
			</CharacterStyleRange>
			<CharacterStyleRange AppliedCharacterStyle="CharacterStyle/$ID/[No character style]" PointSize="10" Tracking="-10">
				<Properties>
					<Leading type="unit">14</Leading>
					<AppliedFont type="string">Montserrat</AppliedFont>
				</Properties>
				<Content>  et de leurs identités locales</Content>
				<Br />
			</CharacterStyleRange>
		</ParagraphStyleRange>
		<ParagraphStyleRange AppliedParagraphStyle="ParagraphStyle/$ID/NormalParagraphStyle" Hyphenation="false" SpaceAfter="2.834645669291339">
			<CharacterStyleRange AppliedCharacterStyle="CharacterStyle/$ID/[No character style]" PointSize="10" Tracking="-10">
				<Properties>
					<Leading type="unit">14</Leading>
					<AppliedFont type="string">Montserrat</AppliedFont>
				</Properties>
				<Content>• <?ACE 7?>Le maintien des </Content>
			</CharacterStyleRange>
			<CharacterStyleRange AppliedCharacterStyle="CharacterStyle/$ID/[No character style]" FontStyle="Bold" PointSize="10" Tracking="-10">
				<Properties>
					<Leading type="unit">14</Leading>
					<AppliedFont type="string">Montserrat</AppliedFont>
				</Properties>
				<Content>lignes secondaires sncf</Content>
				<Br />
				<Content>• <?ACE 7?>Des places en crèches</Content>
			</CharacterStyleRange>
			<CharacterStyleRange AppliedCharacterStyle="CharacterStyle/$ID/[No character style]" PointSize="10" Tracking="-10">
				<Properties>
					<Leading type="unit">14</Leading>
					<AppliedFont type="string">Montserrat</AppliedFont>
				</Properties>
				<Content> </Content>
			</CharacterStyleRange>
			<CharacterStyleRange AppliedCharacterStyle="CharacterStyle/$ID/[No character style]" FontStyle="Bold" PointSize="10" Tracking="-10">
				<Properties>
					<Leading type="unit">14</Leading>
					<AppliedFont type="string">Montserrat</AppliedFont>
				</Properties>
				<Content> </Content>
			</CharacterStyleRange>
			<CharacterStyleRange AppliedCharacterStyle="CharacterStyle/$ID/[No character style]" PointSize="10" Tracking="-10">
				<Properties>
					<Leading type="unit">14</Leading>
					<AppliedFont type="string">Montserrat</AppliedFont>
				</Properties>
				<Content>pour les familles </Content>
				<Br />
			</CharacterStyleRange>
		</ParagraphStyleRange>
		<ParagraphStyleRange AppliedParagraphStyle="ParagraphStyle/$ID/NormalParagraphStyle" Hyphenation="false">
			<CharacterStyleRange AppliedCharacterStyle="CharacterStyle/$ID/[No character style]" FontStyle="Bold" PointSize="10" Tracking="-10">
				<Properties>
					<Leading type="unit">14</Leading>
					<AppliedFont type="string">Montserrat</AppliedFont>
				</Properties>
				<Content>• <?ACE 7?>La priorité de logement</Content>
			</CharacterStyleRange>
			<CharacterStyleRange AppliedCharacterStyle="CharacterStyle/$ID/[No character style]" PointSize="10" Tracking="-10">
				<Properties>
					<Leading type="unit">14</Leading>
					<AppliedFont type="string">Montserrat</AppliedFont>
				</Properties>
				<Content> </Content>
			</CharacterStyleRange>
			<CharacterStyleRange AppliedCharacterStyle="CharacterStyle/$ID/[No character style]" FontStyle="Bold" PointSize="10" Tracking="-10">
				<Properties>
					<Leading type="unit">14</Leading>
					<AppliedFont type="string">Montserrat</AppliedFont>
				</Properties>
				<Content> </Content>
			</CharacterStyleRange>
			<CharacterStyleRange AppliedCharacterStyle="CharacterStyle/$ID/[No character style]" PointSize="10" Tracking="-10">
				<Properties>
					<Leading type="unit">14</Leading>
					<AppliedFont type="string">Montserrat</AppliedFont>
				</Properties>
				<Content>pour les Français</Content>
				<Br />
			</CharacterStyleRange>
		</ParagraphStyleRange>
		<ParagraphStyleRange AppliedParagraphStyle="ParagraphStyle/$ID/NormalParagraphStyle" Hyphenation="false" SpaceBefore="17.007874015748033">
			<CharacterStyleRange AppliedCharacterStyle="CharacterStyle/$ID/[No character style]" PointSize="10" Tracking="-10" Capitalization="AllCaps">
				<Properties>
					<Leading type="unit">14</Leading>
					<AppliedFont type="string">Montserrat</AppliedFont>
				</Properties>
				<Content>Votre volonté respectée</Content>
				<Br />
			</CharacterStyleRange>
		</ParagraphStyleRange>
		<ParagraphStyleRange AppliedParagraphStyle="ParagraphStyle/$ID/NormalParagraphStyle" Hyphenation="false" SpaceBefore="1.4173228346456694" SpaceAfter="2.834645669291339">
			<CharacterStyleRange AppliedCharacterStyle="CharacterStyle/$ID/[No character style]" PointSize="10" Tracking="-10">
				<Properties>
					<Leading type="unit">14</Leading>
					<AppliedFont type="string">Montserrat</AppliedFont>
				</Properties>
				<Content>• <?ACE 7?>L’instauration de </Content>
			</CharacterStyleRange>
			<CharacterStyleRange AppliedCharacterStyle="CharacterStyle/$ID/[No character style]" FontStyle="Bold" PointSize="10" Tracking="-10">
				<Properties>
					<Leading type="unit">14</Leading>
					<AppliedFont type="string">Montserrat</AppliedFont>
				</Properties>
				<Content>la proportionnelle</Content>
				<Br />
			</CharacterStyleRange>
		</ParagraphStyleRange>
		<ParagraphStyleRange AppliedParagraphStyle="ParagraphStyle/$ID/NormalParagraphStyle" Hyphenation="false" SpaceAfter="2.834645669291339">
			<CharacterStyleRange AppliedCharacterStyle="CharacterStyle/$ID/[No character style]" FontStyle="Bold" PointSize="10" Tracking="-10">
				<Properties>
					<Leading type="unit">14</Leading>
					<AppliedFont type="string">Montserrat</AppliedFont>
				</Properties>
				<Content>• <?ACE 7?>Le referendum d’initiative populaire</Content>
			</CharacterStyleRange>
			<CharacterStyleRange AppliedCharacterStyle="CharacterStyle/$ID/[No character style]" PointSize="10" Tracking="-10">
				<Properties>
					<Leading type="unit">14</Leading>
					<AppliedFont type="string">Montserrat</AppliedFont>
				</Properties>
				<Br />
				<Content>• <?ACE 7?>La réforme de </Content>
			</CharacterStyleRange>
			<CharacterStyleRange AppliedCharacterStyle="CharacterStyle/$ID/[No character style]" FontStyle="Bold" PointSize="10" Tracking="-10">
				<Properties>
					<Leading type="unit">14</Leading>
					<AppliedFont type="string">Montserrat</AppliedFont>
				</Properties>
				<Content>la représentativité syndicale</Content>
				<Br />
			</CharacterStyleRange>
		</ParagraphStyleRange>
		<ParagraphStyleRange AppliedParagraphStyle="ParagraphStyle/$ID/NormalParagraphStyle" Hyphenation="false">
			<CharacterStyleRange AppliedCharacterStyle="CharacterStyle/$ID/[No character style]" PointSize="10" Tracking="-10">
				<Properties>
					<Leading type="unit">14</Leading>
					<AppliedFont type="string">Montserrat</AppliedFont>
				</Properties>
				<Content>• <?ACE 7?>Le retour de </Content>
			</CharacterStyleRange>
			<CharacterStyleRange AppliedCharacterStyle="CharacterStyle/$ID/[No character style]" FontStyle="Bold" PointSize="10" Tracking="-10">
				<Properties>
					<Leading type="unit">14</Leading>
					<AppliedFont type="string">Montserrat</AppliedFont>
				</Properties>
				<Content>la souveraineté française</Content>
				<Br />
			</CharacterStyleRange>
			<CharacterStyleRange AppliedCharacterStyle="CharacterStyle/$ID/[No character style]" PointSize="10" Tracking="-10">
				<Properties>
					<Leading type="unit">12</Leading>
					<AppliedFont type="string">Montserrat</AppliedFont>
				</Properties>
				<Br />
			</CharacterStyleRange>
			<CharacterStyleRange AppliedCharacterStyle="CharacterStyle/$ID/[No character style]" PointSize="10" Tracking="-10" Capitalization="AllCaps">
				<Properties>
					<Leading type="unit">14</Leading>
					<AppliedFont type="string">Montserrat</AppliedFont>
				</Properties>
				<Content>Votre sécurité</Content>
				<Br />
			</CharacterStyleRange>
		</ParagraphStyleRange>
		<ParagraphStyleRange AppliedParagraphStyle="ParagraphStyle/$ID/NormalParagraphStyle" Hyphenation="false" SpaceAfter="2.834645669291339">
			<CharacterStyleRange AppliedCharacterStyle="CharacterStyle/$ID/[No character style]" FontStyle="Bold" PointSize="10" Tracking="-10">
				<Properties>
					<Leading type="unit">14</Leading>
					<AppliedFont type="string">Montserrat</AppliedFont>
				</Properties>
				<Content>• <?ACE 7?>La tolérance zéro contre  les délinquants</Content>
			</CharacterStyleRange>
			<CharacterStyleRange AppliedCharacterStyle="CharacterStyle/$ID/[No character style]" PointSize="10" Tracking="-10">
				<Properties>
					<Leading type="unit">14</Leading>
					<AppliedFont type="string">Montserrat</AppliedFont>
				</Properties>
				<Br />
			</CharacterStyleRange>
			<CharacterStyleRange AppliedCharacterStyle="CharacterStyle/$ID/[No character style]" FontStyle="Bold" PointSize="10" Tracking="-10">
				<Properties>
					<Leading type="unit">14</Leading>
					<AppliedFont type="string">Montserrat</AppliedFont>
				</Properties>
				<Content>• <?ACE 7?>La reconquête</Content>
			</CharacterStyleRange>
			<CharacterStyleRange AppliedCharacterStyle="CharacterStyle/$ID/[No character style]" PointSize="10" Tracking="-10">
				<Properties>
					<Leading type="unit">14</Leading>
					<AppliedFont type="string">Montserrat</AppliedFont>
				</Properties>
				<Content> des zones de non droit</Content>
				<Br />
			</CharacterStyleRange>
		</ParagraphStyleRange>
		<ParagraphStyleRange AppliedParagraphStyle="ParagraphStyle/$ID/NormalParagraphStyle" Hyphenation="false">
			<CharacterStyleRange AppliedCharacterStyle="CharacterStyle/$ID/[No character style]" FontStyle="Bold" PointSize="10" Tracking="-10">
				<Properties>
					<Leading type="unit">14</Leading>
					<AppliedFont type="string">Montserrat</AppliedFont>
				</Properties>
				<Content>• <?ACE 7?>L’éradication de l’idéologie islamiste</Content>
			</CharacterStyleRange>
			<CharacterStyleRange AppliedCharacterStyle="CharacterStyle/$ID/[No character style]" PointSize="10" Tracking="-10">
				<Properties>
					<Leading type="unit">14</Leading>
					<AppliedFont type="string">Montserrat</AppliedFont>
				</Properties>
				<Content> qui arme le terrorisme</Content>
			</CharacterStyleRange>
		</ParagraphStyleRange>
	</Story>
</idPkg:Story>
